matha/__init__.py
matha/ai.py
matha-0.2.dist-info/METADATA
matha-0.2.dist-info/WHEEL
matha-0.2.dist-info/top_level.txt
matha-0.2.dist-info/RECORD
